pyituran/__init__.py
pyituran/cmdline.py
pyituran/const.py
pyituran/exceptions.py
pyituran/ituran.py
pyituran/vehicle.py
pyituran-0.1.4.dist-info/LICENSE
pyituran-0.1.4.dist-info/METADATA
pyituran-0.1.4.dist-info/WHEEL
pyituran-0.1.4.dist-info/entry_points.txt
pyituran-0.1.4.dist-info/top_level.txt
pyituran-0.1.4.dist-info/RECORD
