Metadata-Version: 2.1
Name: pyituran
Version: 0.1.4
Summary: A module to interact with Ituran's web service.
Home-page: https://github.com/shmuelzon/pyituran
Author: Shmuelzon
License: MIT
Download-URL: https://github.com/shmuelzon/pyituran/tarball/0.1.4
Platform: UNKNOWN
Requires-Python: >=3.9
License-File: LICENSE
Requires-Dist: aiohttp
Provides-Extra: test
Requires-Dist: black; extra == "test"
Requires-Dist: coverage; extra == "test"
Requires-Dist: flake8; extra == "test"
Requires-Dist: pep8-naming; extra == "test"
Requires-Dist: pytest; extra == "test"
Requires-Dist: pytest-asyncio; extra == "test"
Requires-Dist: pytest-cov; extra == "test"
Requires-Dist: setuptools; extra == "test"
Requires-Dist: wheel; extra == "test"
